colorblind_async.py
colorblind_async-0.0.1.dist-info/LICENSE
colorblind_async-0.0.1.dist-info/METADATA
colorblind_async-0.0.1.dist-info/WHEEL
colorblind_async-0.0.1.dist-info/top_level.txt
colorblind_async-0.0.1.dist-info/RECORD
