Metadata-Version: 2.1
Name: colorblind-async
Version: 0.0.1
Summary: Allows call await from synchronous context
Author-email: tzolkincz <vaclav@happy-robots.cz>
Project-URL: Homepage, https://github.com/tzolkincz/colorblind-async
Project-URL: Bug Tracker, https://github.com/tzolkincz/colorblind-async/issues
Classifier: Programming Language :: Python :: 3
Classifier: License :: OSI Approved :: MIT License
Classifier: Operating System :: OS Independent
Requires-Python: >=3.7
License-File: LICENSE
Requires-Dist: pytest (>=4.2.1)
Requires-Dist: libcst (>=0.3.4)
Requires-Dist: nest-asyncio (>=1.5.0)
Provides-Extra: tests
Requires-Dist: pytest ; extra == 'tests'
